odoo8_addon_event_project-8.0.1.1.1-py2.7-nspkg.pth
odoo_addons/event_project/__openerp__.py
odoo_addons/event_project/__init__.py
odoo_addons/event_project/README.rst
odoo_addons/event_project/security/ir.model.access.csv
odoo_addons/event_project/models/event_event.py
odoo_addons/event_project/models/project_task_work.py
odoo_addons/event_project/models/project_project.py
odoo_addons/event_project/models/project_task.py
odoo_addons/event_project/models/__init__.py
odoo_addons/event_project/i18n/es.po
odoo_addons/event_project/i18n/event_project.pot
odoo_addons/event_project/i18n/sl.po
odoo_addons/event_project/wizard/project_template_wizard.py
odoo_addons/event_project/wizard/project_template_wizard.xml
odoo_addons/event_project/wizard/__init__.py
odoo_addons/event_project/views/project_project_view.xml
odoo_addons/event_project/views/event_event_view.xml
odoo_addons/event_project/views/project_task_view.xml
odoo_addons/event_project/tests/__init__.py
odoo_addons/event_project/tests/test_event_project.py
odoo_addons/event_project/static/description/icon.png
odoo8_addon_event_project-8.0.1.1.1.dist-info/top_level.txt
odoo8_addon_event_project-8.0.1.1.1.dist-info/WHEEL
odoo8_addon_event_project-8.0.1.1.1.dist-info/RECORD
odoo8_addon_event_project-8.0.1.1.1.dist-info/metadata.json
odoo8_addon_event_project-8.0.1.1.1.dist-info/DESCRIPTION.rst
odoo8_addon_event_project-8.0.1.1.1.dist-info/METADATA
odoo8_addon_event_project-8.0.1.1.1.dist-info/namespace_packages.txt
